JingtongPandasTansuoxingFenxiChuyiFix1/README.md
JingtongPandasTansuoxingFenxiChuyiFix1/__init__.py
JingtongPandasTansuoxingFenxiChuyiFix1/__main__.py
JingtongPandasTansuoxingFenxiChuyiFix1/file.epub
JingtongPandasTansuoxingFenxiChuyiFix1/index.html
JingtongPandasTansuoxingFenxiChuyiFix1/css/__init__.py
JingtongPandasTansuoxingFenxiChuyiFix1/css/annotations.css
JingtongPandasTansuoxingFenxiChuyiFix1/css/main.css
JingtongPandasTansuoxingFenxiChuyiFix1/css/normalize.css
JingtongPandasTansuoxingFenxiChuyiFix1/css/popup.css
JingtongPandasTansuoxingFenxiChuyiFix1/font/__init__.py
JingtongPandasTansuoxingFenxiChuyiFix1/font/fontello.eot
JingtongPandasTansuoxingFenxiChuyiFix1/font/fontello.svg
JingtongPandasTansuoxingFenxiChuyiFix1/font/fontello.ttf
JingtongPandasTansuoxingFenxiChuyiFix1/font/fontello.woff
JingtongPandasTansuoxingFenxiChuyiFix1/img/__init__.py
JingtongPandasTansuoxingFenxiChuyiFix1/img/annotator-glyph-sprite.png
JingtongPandasTansuoxingFenxiChuyiFix1/img/annotator-icon-sprite.png
JingtongPandasTansuoxingFenxiChuyiFix1/img/apple-touch-icon.png
JingtongPandasTansuoxingFenxiChuyiFix1/img/cancelfullscreen.png
JingtongPandasTansuoxingFenxiChuyiFix1/img/close.png
JingtongPandasTansuoxingFenxiChuyiFix1/img/fullscreen.png
JingtongPandasTansuoxingFenxiChuyiFix1/img/loader.gif
JingtongPandasTansuoxingFenxiChuyiFix1/img/menu-icon.png
JingtongPandasTansuoxingFenxiChuyiFix1/img/save.png
JingtongPandasTansuoxingFenxiChuyiFix1/img/saved.png
JingtongPandasTansuoxingFenxiChuyiFix1/img/settings-s.png
JingtongPandasTansuoxingFenxiChuyiFix1/img/settings.png
JingtongPandasTansuoxingFenxiChuyiFix1/img/star.png
JingtongPandasTansuoxingFenxiChuyiFix1/js/__init__.py
JingtongPandasTansuoxingFenxiChuyiFix1/js/epub.js
JingtongPandasTansuoxingFenxiChuyiFix1/js/epub.min.js
JingtongPandasTansuoxingFenxiChuyiFix1/js/epub.min.map
JingtongPandasTansuoxingFenxiChuyiFix1/js/hooks.min.js
JingtongPandasTansuoxingFenxiChuyiFix1/js/hooks.min.map
jingtong_pandas_tansuoxing_fenxi_chuyi_fix1-2025.3.24.1.dist-info/METADATA
jingtong_pandas_tansuoxing_fenxi_chuyi_fix1-2025.3.24.1.dist-info/WHEEL
jingtong_pandas_tansuoxing_fenxi_chuyi_fix1-2025.3.24.1.dist-info/entry_points.txt
jingtong_pandas_tansuoxing_fenxi_chuyi_fix1-2025.3.24.1.dist-info/top_level.txt
jingtong_pandas_tansuoxing_fenxi_chuyi_fix1-2025.3.24.1.dist-info/RECORD
